ECAgent/Collectors.py
ECAgent/Core.py
ECAgent/Decode.py
ECAgent/Environments.py
ECAgent/Tags.py
ECAgent/Visualization.py
ECAgent/__init__.py
ECAgent-0.5.5.dist-info/LICENSE
ECAgent-0.5.5.dist-info/METADATA
ECAgent-0.5.5.dist-info/WHEEL
ECAgent-0.5.5.dist-info/top_level.txt
ECAgent-0.5.5.dist-info/RECORD
