Metadata-Version: 2.1
Name: ECAgent
Version: 0.5.5
Summary: An Agent-based Modelling framework based on the Entity-Component-System architectural pattern.
Home-page: https://github.com/BrandonGower-Winter/ECAgent
Author: Brandon Gower-Winter
Author-email: brandongowerwinter@gmail.com
Classifier: Programming Language :: Python :: 3
Classifier: License :: OSI Approved :: MIT License
Classifier: Operating System :: OS Independent
Requires-Python: >=3.7
License-File: LICENSE
Requires-Dist: dash
Requires-Dist: deprecated
Requires-Dist: numpy (>=1.24.2)
Requires-Dist: pandas (>=1.3.5)
